weichen_toolbox2/my_toolbox.py
weichen_toolbox2-0.0.0.dist-info/METADATA
weichen_toolbox2-0.0.0.dist-info/WHEEL
weichen_toolbox2-0.0.0.dist-info/RECORD
