Metadata-Version: 2.1
Name: weichen-toolbox2
Version: 0.0.0
Summary: advanced python caching
License: MIT
Author: weichen74
Author-email: weichen74@sina.com
Requires-Python: >=3.11,<4.0
Classifier: License :: OSI Approved :: MIT License
Classifier: Programming Language :: Python :: 3
Classifier: Programming Language :: Python :: 3.11
Classifier: Programming Language :: Python :: 3.12
Requires-Dist: charset-normalizer (>=3.3.2,<4.0.0)
Requires-Dist: requests (>=2.32.3,<3.0.0)
